W2_report/TDPU/package_def.sv
package package_def;
  typedef enum logic [1:0] {
    W_ZERO = 2'b01,
    W_POS  = 2'b10,
    W_NEG  = 2'b00
  } weight_t;
endpackage

W2_report/TDPU/vec_multi_core.sv
`timescale 1ns / 1ps
`include "package_def.sv"  //引入包定义文件

//在一个时间周期内并行计算默认参数为16对数据的TDPU核心
//该核心先进行权重锁存，然后以脉动形式输出结果
//logic [数量-1 : 0] [位宽-1 : 0] 变量名;
module vec_multi_core #(
    parameter int LEN = 16,  //并行度
    parameter int DATA_WIDTH = 8
) (

    input logic clk,
    input logic rst_n,  //异步复位
    input logic i_data_valid,  //输入数据有效信号（同步）
    input logic i_load_weight,  //加载权重信号（同步）
    input logic signed [LEN-1:0][DATA_WIDTH-1:0] i_data,  //输入激活值数组
    input weight_t [LEN-1:0] i_weight,  //输入权重数组
    output logic o_data_ready,  //输出结果有效信号（同步）
    output logic signed [31:0] o_result  //输出累加结果，选择32位以防溢出
);
  import package_def::*;
  //0.权重寄存器(收到加载信号时锁存权重)
  weight_t [LEN-1:0] weight_reg;
  always_ff @(posedge clk or negedge rst_n) begin : core
    if (!rst_n) begin
      weight_reg <= '{default: W_ZERO};
    end else begin
      if (i_load_weight) begin
        weight_reg <= i_weight;//如果没有收到权重加载信号则保持原来的数据不变
      end
    end

  end

  //1.PE计算层
  //中间信号：用于处理符号扩展
  logic signed [LEN-1:0][31:0] product;
  //计算每个激活值和权重点积的结果（并行生成）
  //根据权重值决定是加、减 还是 不变
  generate
    for (genvar i = 0; i < LEN; i++) begin : gen_PE  // genvar是生成循环专用变量
      always_ff @(posedge clk or negedge rst_n) begin
        if (!rst_n) begin
          product[i] <= 32'sd0;  // 每个元素独立复位
        end else begin
          if (i_data_valid) begin
            unique case (weight_reg[i])
              W_POS: begin
                product[i] <= 32'(i_data[i]);  // 符号扩展到32位
              end
              W_NEG: begin
                product[i] <= -32'(i_data[i]);  // 符号扩展并取负
              end
              W_ZERO: begin
                product[i] <= 32'sd0;
              end
              default: product[i] <= 32'sd0;
            endcase
          end else begin
            // 补充i_data_valid为低时的赋值，避免锁存器
            product[i] <= product[i];  // 保持原值（显式写，消除警告）

          end
        end
      end
    end
  endgenerate


  //2.加法树 Part1
  logic signed [3:0][31:0] sum_temp;  //中间和
  logic o_valid_stage1;//由于加法树分了两层，所以valid信号也要分两段传递，否则时许不收敛

  always_ff @(posedge clk or negedge rst_n) begin
    if (!rst_n) begin
      for (int k = 0; k < 4; k++) sum_temp[k] <= '0;
      o_valid_stage1 <= 1'b0;
    end else begin

      sum_temp[0] <= (product[0] + product[1]) + (product[2] + product[3]);
      sum_temp[1] <= (product[4] + product[5]) + (product[6] + product[7]);
      sum_temp[2] <= (product[8] + product[9]) + (product[10] + product[11]);
      sum_temp[3] <= (product[12] + product[13]) + (product[14] + product[15]);

      o_valid_stage1 <= i_data_valid;
    end
  end

  //3.加法树 Part2 & 输出寄存器
  always_ff @(posedge clk or negedge rst_n) begin
    if (!rst_n) begin
      o_result <= '0;  //复位不可放到加法树part1,否则会计算错误
      o_data_ready <= 1'b0;
    end else begin
      o_data_ready <= o_valid_stage1;
      o_result <= sum_temp[0] + sum_temp[1] + sum_temp[2] + sum_temp[3];
    end
  end


endmodule

W2_report/TDPU/waveform.vcd
$version Generated by VerilatedVcd $end
$timescale 1ps $end
 $scope module TOP $end
  $var wire 1 : clk $end
  $var wire 1 ; rst_n $end
  $var wire 1 < i_data_valid $end
  $var wire 1 = i_load_weight $end
  $var wire 128 > i_data [127:0] $end
  $var wire 32 B i_weight [31:0] $end
  $var wire 1 C o_data_ready $end
  $var wire 32 D o_result [31:0] $end
  $scope module vec_multi_core $end
   $var wire 32 E LEN [31:0] $end
   $var wire 32 F DATA_WIDTH [31:0] $end
   $var wire 1 : clk $end
   $var wire 1 ; rst_n $end
   $var wire 1 < i_data_valid $end
   $var wire 1 = i_load_weight $end
   $var wire 128 > i_data [127:0] $end
   $var wire 32 B i_weight [31:0] $end
   $var wire 1 C o_data_ready $end
   $var wire 32 D o_result [31:0] $end
   $var wire 32 # weight_reg [31:0] $end
   $var wire 512 $ product [511:0] $end
   $var wire 128 4 sum_temp [127:0] $end
   $var wire 1 8 o_valid_stage1 $end
   $scope module unnamedblk1 $end
    $var wire 32 9 k [31:0] $end
   $upscope $end
  $upscope $end
 $upscope $end
$enddefinitions $end


#0
b00000000000000000000000000000000 #
b00000000000000000000000000000000000000000000000000000000000000000000000000000000000000000000000000000000000000000000000000000000000000000000000000000000000000000000000000000000000000000000000000000000000000000000000000000000000000000000000000000000000000000000000000000000000000000000000000000000000000000000000000000000000000000000000000000000000000000000000000000000000000000000000000000000000000000000000000000000000000000000000000000000000000000000000000000000000000000000000000000000000000000000000000000000 $
b00000000000000000000000000000000000000000000000000000000000000000000000000000000000000000000000000000000000000000000000000000000 4
08
b00000000000000000000000000000000 9
1:
0;
0<
0=
b00000000000000000000000000000000000000000000000000000000000000000000000000000000000000000000000000000000000000000000000000000000 >
b00000000000000000000000000000000 B
0C
b00000000000000000000000000000000 D
b00000000000000000000000000010000 E
b00000000000000000000000000001000 F
#1
0:
#2
b01010101010101010101010101010101 #
b00000000000000000000000000000100 9
1:
#3
0:
#4
1:
#5
0:
#6
1:
#7
0:
#8
1:
#9
0:
#10
1:
#11
0:
#12
1:
#13
0:
#14
1:
#15
0:
#16
1:
#17
0:
#18
1:
#19
0:
#20
1:
1;
#21
0:
#22
b10101010101010101010101010101010 #
1:
1=
b10101010101010101010101010101010 B
#23
0:
#24
b00000000000000000000000000001010000000000000000000000000000010100000000000000000000000000000101000000000000000000000000000001010000000000000000000000000000010100000000000000000000000000000101000000000000000000000000000001010000000000000000000000000000010100000000000000000000000000000101000000000000000000000000000001010000000000000000000000000000010100000000000000000000000000000101000000000000000000000000000001010000000000000000000000000000010100000000000000000000000000000101000000000000000000000000000001010 $
18
1:
1<
0=
b00001010000010100000101000001010000010100000101000001010000010100000101000001010000010100000101000001010000010100000101000001010 >
#25
0:
#26
b00000000000000000000000000101000000000000000000000000000001010000000000000000000000000000010100000000000000000000000000000101000 4
08
1:
0<
1C
#27
0:
#28
1:
0C
b00000000000000000000000010100000 D
#29
0:
#30
1:
#31
0:
#32
1:
#33
0:
#34
1:
#35
0:
#36
1:
#37
0:
#38
1:
#39
0:
#40
1:
#41
0:
#42
1:
#43
0:
#44
1:
#45
0:
#46
b00000000000000000000000000000000 #
1:
1=
b00000000000000000000000000000000 B
#47
0:
#48
b11111111111111111111111111111011111111111111111111111111111110111111111111111111111111111111101111111111111111111111111111111011111111111111111111111111111110111111111111111111111111111111101111111111111111111111111111111011111111111111111111111111111110111111111111111111111111111111101111111111111111111111111111111011111111111111111111111111111110111111111111111111111111111111101111111111111111111111111111111011111111111111111111111111111110111111111111111111111111111111101111111111111111111111111111111011 $
18
1:
1<
0=
b00000101000001010000010100000101000001010000010100000101000001010000010100000101000001010000010100000101000001010000010100000101 >
#49
0:
#50
b11111111111111111111111111101100111111111111111111111111111011001111111111111111111111111110110011111111111111111111111111101100 4
08
1:
0<
1C
#51
0:
#52
1:
0C
b11111111111111111111111110110000 D
