W2_report/TDPU/package_def.sv
`timescale 1ns / 1ps
package package_def;
  typedef enum logic [1:0] {
    W_ZERO = 2'b01,
    W_POS  = 2'b10,
    W_NEG  = 2'b00
  } weight_t;
endpackage

W2_report/TDPU/vec_multi_core.sv
`timescale 1ns / 1ps
//`include "package_def.sv"  //引入包定义文件
import package_def::*;
//在一个时间周期内并行计算默认参数为16对数据的TDPU核心
//该核心先进行权重锁存，然后以脉动形式输出结果
//logic [数量-1 : 0] [位宽-1 : 0] 变量名;
module vec_multi_core #(
    parameter int LEN = 16,  //并行度
    parameter int DATA_WIDTH = 8
) (
    input logic clk,
    input logic rst_n,  //异步复位
    input logic i_data_valid,  //输入数据有效信号（同步）
    input logic i_load_weight,  //加载权重信号（同步）
    input logic signed [LEN-1:0][DATA_WIDTH-1:0] i_data,  //输入激活值数组
    input weight_t [LEN-1:0] i_weight,  //输入权重数组
    output logic o_data_ready,  //输出结果有效信号（同步）
    output logic signed [31:0] o_result  //输出累加结果，选择32位以防溢出
);

  //0.权重寄存器(收到加载信号时锁存权重)
  weight_t [LEN-1:0] weight_reg;
  always_ff @(posedge clk or negedge rst_n) begin : core
    if (!rst_n) begin
      weight_reg <= '{default: W_ZERO};
    end else begin
      if (i_load_weight) begin
        weight_reg <= i_weight;//如果没有收到权重加载信号则保持原来的数据不变
      end
    end

  end

  //1.PE计算层
  //中间信号：用于处理符号扩展
  logic signed [LEN-1:0][31:0] product;
  //计算每个激活值和权重点积的结果（并行生成）
  genvar i;
  generate
    for (i = 0; i < LEN; i++) begin : gen_PE

      //根据权重值决定是加、减 还是 不变
      always_comb begin
        unique case (weight_reg[i])
          W_POS: begin
            product[i] = 32'(i_data[i]);  //符号扩展到32位
          end
          W_NEG: begin
            product[i] = -32'(i_data[i]);  //符号扩展到32位并取负
          end
          W_ZERO: begin
            product[i] = 32'sd0;  //权重为0，结果为0
          end
          default: product[i] = 32'sd0;  // 安全保底
        endcase
      end
    end
  endgenerate

  //2.加法树 Part1
  logic signed [3:0][31:0] sum_temp;  //中间和
  logic o_valid_stage1;//由于加法树分了两层，所以valid信号也要分两段传递，否则时许不收敛

  always_ff @(posedge clk or negedge rst_n) begin
    if (!rst_n) begin
      for (int k = 0; k < 4; k++) sum_temp[k] <= '0;
      o_valid_stage1 <= 1'b0;
    end else begin

      sum_temp[0] <= (product[0] + product[1]) + (product[2] + product[3]);
      sum_temp[1] <= (product[4] + product[5]) + (product[6] + product[7]);
      sum_temp[2] <= (product[8] + product[9]) + (product[10] + product[11]);
      sum_temp[3] <= (product[12] + product[13]) + (product[14] + product[15]);

      o_valid_stage1 <= i_data_valid;
    end
  end

  //3.加法树 Part2 & 输出寄存器
  always_ff @(posedge clk or negedge rst_n) begin
    if (!rst_n) begin
      o_result <= '0;  //复位不可放到加法树part1,否则会计算错误
      o_data_ready <= 1'b0;
    end else begin
      o_data_ready <= o_valid_stage1;
      o_result <= sum_temp[0] + sum_temp[1] + sum_temp[2] + sum_temp[3];
    end
  end


endmodule

W2_report/TDPU/wave.vcd
$version Generated by VerilatedVcd $end
$timescale 1ps $end
 $scope module TOP $end
  $var wire 1 : clk $end
  $var wire 1 ; rst_n $end
  $var wire 1 < i_data_valid $end
  $var wire 1 = i_load_weight $end
  $var wire 128 > i_data [127:0] $end
  $var wire 32 B i_weight [31:0] $end
  $var wire 1 C o_data_ready $end
  $var wire 32 D o_result [31:0] $end
  $scope module vec_multi_core $end
   $var wire 32 E LEN [31:0] $end
   $var wire 32 F DATA_WIDTH [31:0] $end
   $var wire 1 : clk $end
   $var wire 1 ; rst_n $end
   $var wire 1 < i_data_valid $end
   $var wire 1 = i_load_weight $end
   $var wire 128 > i_data [127:0] $end
   $var wire 32 B i_weight [31:0] $end
   $var wire 1 C o_data_ready $end
   $var wire 32 D o_result [31:0] $end
   $var wire 32 3 weight_reg [31:0] $end
   $var wire 512 # product [511:0] $end
   $var wire 128 4 sum_temp [127:0] $end
   $var wire 1 8 o_valid_stage1 $end
   $scope module unnamedblk1 $end
    $var wire 32 9 k [31:0] $end
   $upscope $end
  $upscope $end
 $upscope $end
$enddefinitions $end


#0
b00000000000000000000000000000000000000000000000000000000000000000000000000000000000000000000000000000000000000000000000000000000000000000000000000000000000000000000000000000000000000000000000000000000000000000000000000000000000000000000000000000000000000000000000000000000000000000000000000000000000000000000000000000000000000000000000000000000000000000000000000000000000000000000000000000000000000000000000000000000000000000000000000000000000000000000000000000000000000000000000000000000000000000000000000000000 #
b00000000000000000000000000000000 3
b00000000000000000000000000000000000000000000000000000000000000000000000000000000000000000000000000000000000000000000000000000000 4
08
b00000000000000000000000000000000 9
1:
0;
0<
0=
b00000000000000000000000000000000000000000000000000000000000000000000000000000000000000000000000000000000000000000000000000000000 >
b00000000000000000000000000000000 B
0C
b00000000000000000000000000000000 D
b00000000000000000000000000010000 E
b00000000000000000000000000001000 F
#5
0:
#10
1:
1;
#15
0:
#20
b10101010101010101010101010101010 3
1:
1=
b10101010101010101010101010101010 B
#25
0:
#30
1:
0=
#35
0:
#40
b00000000000000000000000000000001000000000000000000000000000000010000000000000000000000000000000100000000000000000000000000000001000000000000000000000000000000010000000000000000000000000000000100000000000000000000000000000001000000000000000000000000000000010000000000000000000000000000000100000000000000000000000000000001000000000000000000000000000000010000000000000000000000000000000100000000000000000000000000000001000000000000000000000000000000010000000000000000000000000000000100000000000000000000000000000001 #
b00000000000000000000000000000100000000000000000000000000000001000000000000000000000000000000010000000000000000000000000000000100 4
18
1:
1<
b00000001000000010000000100000001000000010000000100000001000000010000000100000001000000010000000100000001000000010000000100000001 >
#45
0:
#50
b00000000000000000000000000000000000000000000000000000000000000000000000000000000000000000000000000000000000000000000000000000000000000000000000000000000000000000000000000000000000000000000000000000000000000000000000000000000000000000000000000000000000000000000000000000000000000000000000000000000000000000000000000000000000000000000000000000000000000000000000000000000000000000000000000000000000000000000000000000000000000000000000000000000000000000000000000000000000000000000000000000000000000000000000000000000 #
b00000000000000000000000000000000000000000000000000000000000000000000000000000000000000000000000000000000000000000000000000000000 4
08
1:
0<
b00000000000000000000000000000000000000000000000000000000000000000000000000000000000000000000000000000000000000000000000000000000 >
1C
b00000000000000000000000000010000 D
#55
0:
#60
1:
0C
b00000000000000000000000000000000 D
#65
0:
#70
1:
#75
0:
#80
b00000000000000001010101010101010 3
1:
1=
b00000000000000001010101010101010 B
#85
0:
#90
1:
0=
#95
0:
#100
b11111111111111111111111111111110111111111111111111111111111111101111111111111111111111111111111011111111111111111111111111111110111111111111111111111111111111101111111111111111111111111111111011111111111111111111111111111110111111111111111111111111111111100000000000000000000000000000001000000000000000000000000000000010000000000000000000000000000000100000000000000000000000000000001000000000000000000000000000000010000000000000000000000000000000100000000000000000000000000000001000000000000000000000000000000010 #
b11111111111111111111111111111000111111111111111111111111111110000000000000000000000000000000100000000000000000000000000000001000 4
18
1:
1<
b00000010000000100000001000000010000000100000001000000010000000100000001000000010000000100000001000000010000000100000001000000010 >
#105
0:
#110
08
1:
0<
1C
#115
0:
#120
1:
0C
